Workbook

Sheet Dashboard
A2: DIY retailer sustainability review
A3: Portfolio demonstration. 2025 operating data for one fictional store and five sample products.
A4: Review date | C4: 46292 | F4: Amber cells are inputs. Pale green cells contain calculations.
A6: Supplier evidence readiness | F6: High-priority suppliers | K6: Overdue actions
A7: =Suppliers!V4 -> 0 | F7: =Suppliers!V5 -> 3 | K7: =Actions!R5 -> 0
A9: Current claim evidence, 5 suppliers | F9: Evidence gaps needing attention | K9: Based on the review date
A11: Store waste recycled | F11: Packaging sold in 2025 | K11: Planned resource cost
A12: =ESG_Monthly!J14 -> 0.69619835 | F12: =Packaging!R6 -> 3132 | K12: =Costs!K12 -> 3806
A14: 2025 weighted annual rate | F14: Sample products; estimated kg | K14: Includes staff time and contingency
A33: Action priority | B33: Open | C33: Overdue | D33: Closed | F33: 2025 energy-related CO2 estimates
A34: High | B34: =COUNTIFS(Actions!$F$2:$F$14, A34, Actions!$L$2:$L$14, "<>Closed") -> 7 | C34: =COUNTIFS(Actions!$F$2:$F$14, A34, Actions!$L$2:$L$14, "Overdue") -> 0 | D34: =COUNTIFS(Actions!$F$2:$F$14, A34, Actions!$L$2:$L$14, "Closed") -> 0 | F34: Electricity consumption (tonnes CO2) | L34: =IF(ISNUMBER(ESG_Monthly!H14), ESG_Monthly!H14 / 1000, "Incomplete") -> 25.97114
A35: Medium | B35: =COUNTIFS(Actions!$F$2:$F$14, A35, Actions!$L$2:$L$14, "<>Closed") -> 6 | C35: =COUNTIFS(Actions!$F$2:$F$14, A35, Actions!$L$2:$L$14, "Overdue") -> 0 | D35: =COUNTIFS(Actions!$F$2:$F$14, A35, Actions!$L$2:$L$14, "Closed") -> 0 | F35: Natural gas combustion (tonnes CO2) | L35: =IF(ISNUMBER(ESG_Monthly!I14), ESG_Monthly!I14 / 1000, "Incomplete") -> 19.90975
A36: Low | B36: =COUNTIFS(Actions!$F$2:$F$14, A36, Actions!$L$2:$L$14, "<>Closed") -> 0 | C36: =COUNTIFS(Actions!$F$2:$F$14, A36, Actions!$L$2:$L$14, "Overdue") -> 0 | D36: =COUNTIFS(Actions!$F$2:$F$14, A36, Actions!$L$2:$L$14, "Closed") -> 0
F37: CO2-only estimates. Electricity includes losses and excludes emissions outside Ireland. These results are not a complete Scope 1 and Scope 2 inventory.
A38: Evidence remains unverified even when input fields are complete.
A42: The data is synthetic. This workbook supports evidence collection, review and planning; it does not certify supplier or legal compliance.

Sheet Actions
A1: Action_ID | B1: Topic | C1: Linked_ID | D1: Action | E1: Internal_Owner | F1: Priority | G1: Start_Date | H1: Due_Date | I1: Status | J1: Completion_Date | K1: Closure_Evidence | L1: Due_Status | M1: Days_Overdue | N1: Closure_Check | O1: Data_Type | Q1: Action metrics | R1: Value
A2: ACT001 | B2: Supplier evidence | C2: SUP001 | D2: =_xlfn.XLOOKUP(C2, Suppliers!$A$2:$A$501, Suppliers!$J$2:$J$501, "Check supplier ID") -> Request sourcing certificate and documents linking it to the supplied timber | E2: =_xlfn.XLOOKUP(C2, Suppliers!$A$2:$A$501, Suppliers!$E$2:$E$501, "Check supplier ID") -> Garden Category Manager | F2: =_xlfn.XLOOKUP(C2, Suppliers!$A$2:$A$501, Suppliers!$Q$2:$Q$501, "Check supplier ID") -> High | G2: =_xlfn.XLOOKUP(C2, Suppliers!$A$2:$A$501, Suppliers!$K$2:$K$501, "Check supplier ID") -> 46293 | H2: =_xlfn.XLOOKUP(C2, Suppliers!$A$2:$A$501, Suppliers!$L$2:$L$501, "Check supplier ID") -> 46307 | I2: =_xlfn.XLOOKUP(C2, Suppliers!$A$2:$A$501, Suppliers!$M$2:$M$501, "Check supplier ID") -> Awaiting response | L2: =_xlfn.IFS( I2 = "", "Missing status", AND(I2 = "Closed", N2 <> "Complete"), "Closure incomplete", I2 = "Closed", "Closed", H2 = "", "Missing deadline", G2 > Dashboard!$C$4, "Scheduled", Dashboard!$C$4 > H2, "Overdue", Dashboard!$C$4 = H2, "Due today", H2 - Dashboard!$C$4 <= 7, "Due soon", TRUE, "Within deadline" ) -> Scheduled | M2: =IF(L2 = "Overdue", Dashboard!$C$4 - H2, 0) -> 0 | N2: =IF(I2 <> "Closed", "Open", IF(OR(J2 = "", K2 = "", K2 = "Not provided"), "Missing closure evidence", "Complete")) -> Open | O2: Synthetic | Q2: Total actions | R2: =COUNTA(A2:A14) -> 13
A3: ACT002 | B3: Supplier evidence | C3: SUP002 | D3: =_xlfn.XLOOKUP(C3, Suppliers!$A$2:$A$501, Suppliers!$J$2:$J$501, "Check supplier ID") -> Check the stated VOC content and which paint products the document covers | E3: =_xlfn.XLOOKUP(C3, Suppliers!$A$2:$A$501, Suppliers!$E$2:$E$501, "Check supplier ID") -> Paint Category Manager | F3: =_xlfn.XLOOKUP(C3, Suppliers!$A$2:$A$501, Suppliers!$Q$2:$Q$501, "Check supplier ID") -> Medium | G3: =_xlfn.XLOOKUP(C3, Suppliers!$A$2:$A$501, Suppliers!$K$2:$K$501, "Check supplier ID") -> 46293 | H3: =_xlfn.XLOOKUP(C3, Suppliers!$A$2:$A$501, Suppliers!$L$2:$L$501, "Check supplier ID") -> 46307 | I3: =_xlfn.XLOOKUP(C3, Suppliers!$A$2:$A$501, Suppliers!$M$2:$M$501, "Check supplier ID") -> Under review | L3: =_xlfn.IFS( I3 = "", "Missing status", AND(I3 = "Closed", N3 <> "Complete"), "Closure incomplete", I3 = "Closed", "Closed", H3 = "", "Missing deadline", G3 > Dashboard!$C$4, "Scheduled", Dashboard!$C$4 > H3, "Overdue", Dashboard!$C$4 = H3, "Due today", H3 - Dashboard!$C$4 <= 7, "Due soon", TRUE, "Within deadline" ) -> Scheduled | M3: =IF(L3 = "Overdue", Dashboard!$C$4 - H3, 0) -> 0 | N3: =IF(I3 <> "Closed", "Open", IF(OR(J3 = "", K3 = "", K3 = "Not provided"), "Missing closure evidence", "Complete")) -> Open | O3: Synthetic | Q3: Closed with evidence | R3: =COUNTIFS(L2:L14, "Closed") -> 0
A4: ACT003 | B4: Supplier evidence | C4: SUP003 | D4: =_xlfn.XLOOKUP(C4, Suppliers!$A$2:$A$501, Suppliers!$J$2:$J$501, "Check supplier ID") -> Request model-specific energy performance evidence and check it against the claim | E4: =_xlfn.XLOOKUP(C4, Suppliers!$A$2:$A$501, Suppliers!$E$2:$E$501, "Check supplier ID") -> Lighting Category Manager | F4: =_xlfn.XLOOKUP(C4, Suppliers!$A$2:$A$501, Suppliers!$Q$2:$Q$501, "Check supplier ID") -> Medium | G4: =_xlfn.XLOOKUP(C4, Suppliers!$A$2:$A$501, Suppliers!$K$2:$K$501, "Check supplier ID") -> 46293 | H4: =_xlfn.XLOOKUP(C4, Suppliers!$A$2:$A$501, Suppliers!$L$2:$L$501, "Check supplier ID") -> 46307 | I4: =_xlfn.XLOOKUP(C4, Suppliers!$A$2:$A$501, Suppliers!$M$2:$M$501, "Check supplier ID") -> Awaiting response | L4: =_xlfn.IFS( I4 = "", "Missing status", AND(I4 = "Closed", N4 <> "Complete"), "Closure incomplete", I4 = "Closed", "Closed", H4 = "", "Missing deadline", G4 > Dashboard!$C$4, "Scheduled", Dashboard!$C$4 > H4, "Overdue", Dashboard!$C$4 = H4, "Due today", H4 - Dashboard!$C$4 <= 7, "Due soon", TRUE, "Within deadline" ) -> Scheduled | M4: =IF(L4 = "Overdue", Dashboard!$C$4 - H4, 0) -> 0 | N4: =IF(I4 <> "Closed", "Open", IF(OR(J4 = "", K4 = "", K4 = "Not provided"), "Missing closure evidence", "Complete")) -> Open | O4: Synthetic | Q4: Open actions | R4: =R2 - R3 -> 13
A5: ACT004 | B5: Supplier evidence | C5: SUP004 | D5: =_xlfn.XLOOKUP(C5, Suppliers!$A$2:$A$501, Suppliers!$J$2:$J$501, "Check supplier ID") -> Request evidence supporting the 80% recycled-content claim, confirm which packaging components it covers, and ask where the recycled material is sourced. | E5: =_xlfn.XLOOKUP(C5, Suppliers!$A$2:$A$501, Suppliers!$E$2:$E$501, "Check supplier ID") -> Tools Category Manager | F5: =_xlfn.XLOOKUP(C5, Suppliers!$A$2:$A$501, Suppliers!$Q$2:$Q$501, "Check supplier ID") -> High | G5: =_xlfn.XLOOKUP(C5, Suppliers!$A$2:$A$501, Suppliers!$K$2:$K$501, "Check supplier ID") -> 46293 | H5: =_xlfn.XLOOKUP(C5, Suppliers!$A$2:$A$501, Suppliers!$L$2:$L$501, "Check supplier ID") -> 46307 | I5: =_xlfn.XLOOKUP(C5, Suppliers!$A$2:$A$501, Suppliers!$M$2:$M$501, "Check supplier ID") -> Awaiting response | L5: =_xlfn.IFS( I5 = "", "Missing status", AND(I5 = "Closed", N5 <> "Complete"), "Closure incomplete", I5 = "Closed", "Closed", H5 = "", "Missing deadline", G5 > Dashboard!$C$4, "Scheduled", Dashboard!$C$4 > H5, "Overdue", Dashboard!$C$4 = H5, "Due today", H5 - Dashboard!$C$4 <= 7, "Due soon", TRUE, "Within deadline" ) -> Scheduled | M5: =IF(L5 = "Overdue", Dashboard!$C$4 - H5, 0) -> 0 | N5: =IF(I5 <> "Closed", "Open", IF(OR(J5 = "", K5 = "", K5 = "Not provided"), "Missing closure evidence", "Complete")) -> Open | O5: Synthetic | Q5: Overdue | R5: =COUNTIFS(L2:L14, "Overdue") -> 0
A6: ACT005 | B6: Supplier evidence | C6: SUP005 | D6: =_xlfn.XLOOKUP(C6, Suppliers!$A$2:$A$501, Suppliers!$J$2:$J$501, "Check supplier ID") -> Request a current certificate and check that it covers the relevant supplier and timber products | E6: =_xlfn.XLOOKUP(C6, Suppliers!$A$2:$A$501, Suppliers!$E$2:$E$501, "Check supplier ID") -> Garden Category Manager | F6: =_xlfn.XLOOKUP(C6, Suppliers!$A$2:$A$501, Suppliers!$Q$2:$Q$501, "Check supplier ID") -> High | G6: =_xlfn.XLOOKUP(C6, Suppliers!$A$2:$A$501, Suppliers!$K$2:$K$501, "Check supplier ID") -> 46293 | H6: =_xlfn.XLOOKUP(C6, Suppliers!$A$2:$A$501, Suppliers!$L$2:$L$501, "Check supplier ID") -> 46307 | I6: =_xlfn.XLOOKUP(C6, Suppliers!$A$2:$A$501, Suppliers!$M$2:$M$501, "Check supplier ID") -> Awaiting response | L6: =_xlfn.IFS( I6 = "", "Missing status", AND(I6 = "Closed", N6 <> "Complete"), "Closure incomplete", I6 = "Closed", "Closed", H6 = "", "Missing deadline", G6 > Dashboard!$C$4, "Scheduled", Dashboard!$C$4 > H6, "Overdue", Dashboard!$C$4 = H6, "Due today", H6 - Dashboard!$C$4 <= 7, "Due soon", TRUE, "Within deadline" ) -> Scheduled | M6: =IF(L6 = "Overdue", Dashboard!$C$4 - H6, 0) -> 0 | N6: =IF(I6 <> "Closed", "Open", IF(OR(J6 = "", K6 = "", K6 = "Not provided"), "Missing closure evidence", "Complete")) -> Open | O6: Synthetic | Q6: Due soon or today | R6: =COUNTIFS(L2:L14, "Due soon") + COUNTIFS(L2:L14, "Due today") -> 1
A7: ACT006 | B7: Packaging data | C7: All components | D7: Obtain measured component weights and linked evidence. | E7: Commercial and Suppliers | F7: Medium | G7: 46293 | H7: 46311 | I7: Not started | L7: =_xlfn.IFS( I7 = "", "Missing status", AND(I7 = "Closed", N7 <> "Complete"), "Closure incomplete", I7 = "Closed", "Closed", H7 = "", "Missing deadline", G7 > Dashboard!$C$4, "Scheduled", Dashboard!$C$4 > H7, "Overdue", Dashboard!$C$4 = H7, "Due today", H7 - Dashboard!$C$4 <= 7, "Due soon", TRUE, "Within deadline" ) -> Scheduled | M7: =IF(L7 = "Overdue", Dashboard!$C$4 - H7, 0) -> 0 | N7: =IF(I7 <> "Closed", "Open", IF(OR(J7 = "", K7 = "", K7 = "Not provided"), "Missing closure evidence", "Complete")) -> Open | O7: Synthetic | Q7: Closure incomplete | R7: =COUNTIFS(L2:L14, "Closure incomplete") -> 0
A8: ACT007 | B8: Claims review | C8: REG001 | D8: Review public claim wording and record approval or withdrawal. | E8: Commercial and Marketing | F8: High | G8: 46292 | H8: 46295 | I8: Not started | L8: =_xlfn.IFS( I8 = "", "Missing status", AND(I8 = "Closed", N8 <> "Complete"), "Closure incomplete", I8 = "Closed", "Closed", H8 = "", "Missing deadline", G8 > Dashboard!$C$4, "Scheduled", Dashboard!$C$4 > H8, "Overdue", Dashboard!$C$4 = H8, "Due today", H8 - Dashboard!$C$4 <= 7, "Due soon", TRUE, "Within deadline" ) -> Due soon | M8: =IF(L8 = "Overdue", Dashboard!$C$4 - H8, 0) -> 0 | N8: =IF(I8 <> "Closed", "Open", IF(OR(J8 = "", K8 = "", K8 = "Not provided"), "Missing closure evidence", "Complete")) -> Open | O8: Synthetic
A9: ACT008 | B9: Timber screening | C9: REG003 | D9: Confirm product codes, retailer role, size and timber traceability requirements. | E9: Sustainability Manager | F9: High | G9: 46293 | H9: 46304 | I9: Not started | L9: =_xlfn.IFS( I9 = "", "Missing status", AND(I9 = "Closed", N9 <> "Complete"), "Closure incomplete", I9 = "Closed", "Closed", H9 = "", "Missing deadline", G9 > Dashboard!$C$4, "Scheduled", Dashboard!$C$4 > H9, "Overdue", Dashboard!$C$4 = H9, "Due today", H9 - Dashboard!$C$4 <= 7, "Due soon", TRUE, "Within deadline" ) -> Scheduled | M9: =IF(L9 = "Overdue", Dashboard!$C$4 - H9, 0) -> 0 | N9: =IF(I9 <> "Closed", "Open", IF(OR(J9 = "", K9 = "", K9 = "Not provided"), "Missing closure evidence", "Complete")) -> Open | O9: Synthetic
A10: ACT009 | B10: Activity evidence | C10: STORE01 | D10: Replace demo activity data with bills and waste records in a real deployment. | E10: Operations and Finance | F10: Medium | G10: 46293 | H10: 46318 | I10: Not started | L10: =_xlfn.IFS( I10 = "", "Missing status", AND(I10 = "Closed", N10 <> "Complete"), "Closure incomplete", I10 = "Closed", "Closed", H10 = "", "Missing deadline", G10 > Dashboard!$C$4, "Scheduled", Dashboard!$C$4 > H10, "Overdue", Dashboard!$C$4 = H10, "Due today", H10 - Dashboard!$C$4 <= 7, "Due soon", TRUE, "Within deadline" ) -> Scheduled | M10: =IF(L10 = "Overdue", Dashboard!$C$4 - H10, 0) -> 0 | N10: =IF(I10 <> "Closed", "Open", IF(OR(J10 = "", K10 = "", K10 = "Not provided"), "Missing closure evidence", "Complete")) -> Open | O10: Synthetic | Q10: ACT001 to ACT005 link to Suppliers. Edit the supplier status there. Other task dates and owners are planning assumptions. A Closed status needs both a completion date and a closure reference.
A11: ACT010 | B11: GHG boundary | C11: STORE01 | D11: Define the full inventory boundary, other gases and the electricity method. | E11: Sustainability Manager | F11: Medium | G11: 46293 | H11: 46318 | I11: Not started | L11: =_xlfn.IFS( I11 = "", "Missing status", AND(I11 = "Closed", N11 <> "Complete"), "Closure incomplete", I11 = "Closed", "Closed", H11 = "", "Missing deadline", G11 > Dashboard!$C$4, "Scheduled", Dashboard!$C$4 > H11, "Overdue", Dashboard!$C$4 = H11, "Due today", H11 - Dashboard!$C$4 <= 7, "Due soon", TRUE, "Within deadline" ) -> Scheduled | M11: =IF(L11 = "Overdue", Dashboard!$C$4 - H11, 0) -> 0 | N11: =IF(I11 <> "Closed", "Open", IF(OR(J11 = "", K11 = "", K11 = "Not provided"), "Missing closure evidence", "Complete")) -> Open | O11: Synthetic
A12: ACT011 | B12: WEEE review | C12: REG006 | D12: Check electrical producer registration, take-back arrangements and records. | E12: Operations Manager | F12: High | G12: 46293 | H12: 46297 | I12: Not started | L12: =_xlfn.IFS( I12 = "", "Missing status", AND(I12 = "Closed", N12 <> "Complete"), "Closure incomplete", I12 = "Closed", "Closed", H12 = "", "Missing deadline", G12 > Dashboard!$C$4, "Scheduled", Dashboard!$C$4 > H12, "Overdue", Dashboard!$C$4 = H12, "Due today", H12 - Dashboard!$C$4 <= 7, "Due soon", TRUE, "Within deadline" ) -> Scheduled | M12: =IF(L12 = "Overdue", Dashboard!$C$4 - H12, 0) -> 0 | N12: =IF(I12 <> "Closed", "Open", IF(OR(J12 = "", K12 = "", K12 = "Not provided"), "Missing closure evidence", "Complete")) -> Open | O12: Synthetic
A13: ACT012 | B13: Lighting scope | C13: REG005 | D13: Confirm light-source classification and the applicable label and model data. | E13: Lighting Category Manager | F13: Medium | G13: 46293 | H13: 46304 | I13: Not started | L13: =_xlfn.IFS( I13 = "", "Missing status", AND(I13 = "Closed", N13 <> "Complete"), "Closure incomplete", I13 = "Closed", "Closed", H13 = "", "Missing deadline", G13 > Dashboard!$C$4, "Scheduled", Dashboard!$C$4 > H13, "Overdue", Dashboard!$C$4 = H13, "Due today", H13 - Dashboard!$C$4 <= 7, "Due soon", TRUE, "Within deadline" ) -> Scheduled | M13: =IF(L13 = "Overdue", Dashboard!$C$4 - H13, 0) -> 0 | N13: =IF(I13 <> "Closed", "Open", IF(OR(J13 = "", K13 = "", K13 = "Not provided"), "Missing closure evidence", "Complete")) -> Open | O13: Synthetic
A14: ACT013 | B14: Packaging scope | C14: REG002 | D14: Map PPWR duties, phased dates and Irish producer-responsibility requirements. | E14: Sustainability Manager | F14: High | G14: 46293 | H14: 46297 | I14: Not started | L14: =_xlfn.IFS( I14 = "", "Missing status", AND(I14 = "Closed", N14 <> "Complete"), "Closure incomplete", I14 = "Closed", "Closed", H14 = "", "Missing deadline", G14 > Dashboard!$C$4, "Scheduled", Dashboard!$C$4 > H14, "Overdue", Dashboard!$C$4 = H14, "Due today", H14 - Dashboard!$C$4 <= 7, "Due soon", TRUE, "Within deadline" ) -> Scheduled | M14: =IF(L14 = "Overdue", Dashboard!$C$4 - H14, 0) -> 0 | N14: =IF(I14 <> "Closed", "Open", IF(OR(J14 = "", K14 = "", K14 = "Not provided"), "Missing closure evidence", "Complete")) -> Open | O14: Synthetic

Sheet Suppliers
A1: Supplier_ID | B1: Supplier_Name | C1: Supplier_Country | D1: Main_Category | E1: Internal_Owner | F1: Data_Type | G1: Sustainability_Claim | H1: Evidence_Status | I1: Verification_Status | J1: Next_Action | K1: Request_Date | L1: Due_Date | M1: Follow_Up_Status | N1: Evidence_Reference | O1: Review_Notes | P1: Due_Status | Q1: Priority | R1: Priority_Reason | S1: Claim_Use_Status | U1: Supplier metrics | V1: Value
A2: SUP001 | B2: Demo Timber Ltd | C2: Ireland | D2: Timber & Garden | E2: Garden Category Manager | F2: Synthetic | G2: Timber comes from responsibly managed forests | H2: Not received | I2: Unverified | J2: Request sourcing certificate and documents linking it to the supplied timber | K2: 46293 | L2: 46307 | M2: Awaiting response | N2: Not provided | O2: Sourcing claim cannot be checked until supporting evidence is received | P2: =_xlfn.IFS( M2 <> "Awaiting response", "", L2 = "", "Missing deadline", K2 > Dashboard!$C$4, "Scheduled", Dashboard!$C$4 > L2, "Overdue", TRUE, "Within deadline" ) -> Scheduled | Q2: High | R2: Sourcing claim has no supporting evidence. | S2: =_xlfn.IFS( I2 <> "Verified", "Hold claim", OR(N2 = "", N2 = "Not provided", N2 = "Demo document pending"), "Evidence reference missing", H2 = "Expired certificate", "Current evidence needed", TRUE, "Ready for approval" ) -> Hold claim | U2: Suppliers | V2: =COUNTA(A2:A501) -> 5
A3: SUP002 | B3: Demo Paint Palace Ltd | C3: India | D3: Paint | E3: Paint Category Manager | F3: Synthetic | G3: Paint has low VOC content | H3: Technical data sheet received; review pending | I3: Unverified | J3: Check the stated VOC content and which paint products the document covers | K3: 46293 | L3: 46307 | M3: Under review | N3: Demo document pending | O3: Technical data sheet needs review for VOC content and product coverage | P3: =_xlfn.IFS( M3 <> "Awaiting response", "", L3 = "", "Missing deadline", K3 > Dashboard!$C$4, "Scheduled", Dashboard!$C$4 > L3, "Overdue", TRUE, "Within deadline" ) | Q3: Medium | R3: Technical document is recorded as received but still needs review. | S3: =_xlfn.IFS( I3 <> "Verified", "Hold claim", OR(N3 = "", N3 = "Not provided", N3 = "Demo document pending"), "Evidence reference missing", H3 = "Expired certificate", "Current evidence needed", TRUE, "Ready for approval" ) -> Hold claim | U3: Evidence ready | V3: =COUNTIFS(S2:S501, "Ready for approval") -> 0
A4: SUP003 | B4: Demo Lighting Solutions Ltd | C4: China | D4: Lighting | E4: Lighting Category Manager | F4: Synthetic | G4: Lighting products are energy-efficient | H4: Product specifications received; review pending | I4: Unverified | J4: Request model-specific energy performance evidence and check it against the claim | K4: 46293 | L4: 46307 | M4: Awaiting response | N4: Demo document pending | O4: Specifications need review for model-specific energy performance | P4: =_xlfn.IFS( M4 <> "Awaiting response", "", L4 = "", "Missing deadline", K4 > Dashboard!$C$4, "Scheduled", Dashboard!$C$4 > L4, "Overdue", TRUE, "Within deadline" ) -> Scheduled | Q4: Medium | R4: Model-specific performance still needs checking. | S4: =_xlfn.IFS( I4 <> "Verified", "Hold claim", OR(N4 = "", N4 = "Not provided", N4 = "Demo document pending"), "Evidence reference missing", H4 = "Expired certificate", "Current evidence needed", TRUE, "Ready for approval" ) -> Hold claim | U4: Evidence readiness | V4: =IF(V2 = 0, "n.a.", V3 / V2) -> 0
A5: SUP004 | B5: Demo EverydayTools Ltd | C5: China | D5: Tools | E5: Tools Category Manager | F5: Synthetic | G5: Tool packaging contains 80% recycled material | H5: Supplier statement received; supporting evidence missing | I5: Unverified | J5: Request evidence supporting the 80% recycled-content claim, confirm which packaging components it covers, and ask where the recycled material is sourced. | K5: 46293 | L5: 46307 | M5: Awaiting response | N5: Demo document pending | O5: Supplier statement does not substantiate 80%; percentage, components and material source need checking | P5: =_xlfn.IFS( M5 <> "Awaiting response", "", L5 = "", "Missing deadline", K5 > Dashboard!$C$4, "Scheduled", Dashboard!$C$4 > L5, "Overdue", TRUE, "Within deadline" ) -> Scheduled | Q5: High | R5: The 80% claim has no proof of percentage, components or source. | S5: =_xlfn.IFS( I5 <> "Verified", "Hold claim", OR(N5 = "", N5 = "Not provided", N5 = "Demo document pending"), "Evidence reference missing", H5 = "Expired certificate", "Current evidence needed", TRUE, "Ready for approval" ) -> Hold claim | U5: High priority | V5: =COUNTIFS(Q2:Q501, "High", S2:S501, "<>Ready for approval") -> 3
A6: SUP005 | B6: Demo Garden King Ltd | C6: Ireland | D6: Garden Furniture | E6: Garden Category Manager | F6: Synthetic | G6: Timber is eco-friendly | H6: Expired certificate | I6: Unverified | J6: Request a current certificate and check that it covers the relevant supplier and timber products | K6: 46293 | L6: 46307 | M6: Awaiting response | N6: Demo document pending | O6: Certificate has expired; request current evidence and check product coverage | P6: =_xlfn.IFS( M6 <> "Awaiting response", "", L6 = "", "Missing deadline", K6 > Dashboard!$C$4, "Scheduled", Dashboard!$C$4 > L6, "Overdue", TRUE, "Within deadline" ) -> Scheduled | Q6: High | R6: Certificate has expired and the environmental claim is broad. | S6: =_xlfn.IFS( I6 <> "Verified", "Hold claim", OR(N6 = "", N6 = "Not provided", N6 = "Demo document pending"), "Evidence reference missing", H6 = "Expired certificate", "Current evidence needed", TRUE, "Ready for approval" ) -> Hold claim | U6: Unverified claims | V6: =COUNTIFS(I2:I501, "Unverified") -> 5
U7: Expired certificates | V7: =COUNTIFS(H2:H501, "Expired certificate") -> 1
U8: Response overdue | V8: =COUNTIFS(P2:P501, "Overdue") -> 0
U10: Priority is a project judgement about evidence gaps. It is not a legal risk score. Ready for approval still requires a claim wording and product scope decision.

Sheet Products
A1: Product_ID | B1: Supplier_ID | C1: Product_Name | D1: Category | E1: Units_Sold_2025 | F1: Data_Type | G1: Supplier_Name | H1: Supplier_Link_Status | K1: Product metrics | L1: Value
A2: PR001 | B2: SUP001 | C2: Timber fence panel | D2: Timber & Garden | E2: 1200 | F2: Synthetic | G2: =IF(H2 <> "Linked", "Check supplier ID", _xlfn.XLOOKUP(B2, Suppliers!$A$2:$A$501, Suppliers!$B$2:$B$501)) -> Demo Timber Ltd | H2: =IF(COUNTIFS(Suppliers!$A$2:$A$501, B2) = 1, "Linked", "Check supplier ID") -> Linked | K2: Sample products | L2: =COUNTA(A2:A501) -> 5
A3: PR002 | B3: SUP002 | C3: Interior paint 5L | D3: Paint | E3: 5000 | F3: Synthetic | G3: =IF(H3 <> "Linked", "Check supplier ID", _xlfn.XLOOKUP(B3, Suppliers!$A$2:$A$501, Suppliers!$B$2:$B$501)) -> Demo Paint Palace Ltd | H3: =IF(COUNTIFS(Suppliers!$A$2:$A$501, B3) = 1, "Linked", "Check supplier ID") -> Linked | K3: Units sold in 2025 | L3: =SUM(E2:E501) -> 12000
A4: PR003 | B4: SUP003 | C4: LED ceiling light | D4: Lighting | E4: 3000 | F4: Synthetic | G4: =IF(H4 <> "Linked", "Check supplier ID", _xlfn.XLOOKUP(B4, Suppliers!$A$2:$A$501, Suppliers!$B$2:$B$501)) -> Demo Lighting Solutions Ltd | H4: =IF(COUNTIFS(Suppliers!$A$2:$A$501, B4) = 1, "Linked", "Check supplier ID") -> Linked
A5: PR004 | B5: SUP004 | C5: 20-piece tool set | D5: Tools | E5: 2000 | F5: Synthetic | G5: =IF(H5 <> "Linked", "Check supplier ID", _xlfn.XLOOKUP(B5, Suppliers!$A$2:$A$501, Suppliers!$B$2:$B$501)) -> Demo EverydayTools Ltd | H5: =IF(COUNTIFS(Suppliers!$A$2:$A$501, B5) = 1, "Linked", "Check supplier ID") -> Linked
A6: PR005 | B6: SUP005 | C6: Wooden garden chair | D6: Garden Furniture | E6: 800 | F6: Synthetic | G6: =IF(H6 <> "Linked", "Check supplier ID", _xlfn.XLOOKUP(B6, Suppliers!$A$2:$A$501, Suppliers!$B$2:$B$501)) -> Demo Garden King Ltd | H6: =IF(COUNTIFS(Suppliers!$A$2:$A$501, B6) = 1, "Linked", "Check supplier ID") -> Linked | K6: The five products are a sample. Their volumes do not establish entity-wide packaging obligations or company turnover.

Sheet Packaging
A1: Packaging_ID | B1: Product_ID | C1: Component | D1: Material | E1: Estimated_Weight_g_Per_Unit | F1: Evidence_Status | G1: Data_Type | H1: Units_Sold_2025 | I1: Annual_Packaging_kg | J1: Verified_Recycled_Content | K1: Recycled_Material_Source | L1: Recycled_Evidence_Reference | M1: Recycled_Verification | N1: Weight_Record_Status | O1: Weight_Evidence_Reference | Q1: Packaging metrics | R1: Value
A2: PK001 | B2: PR001 | C2: Protective film | D2: Plastic | E2: 60 | F2: Not provided | G2: Synthetic | H2: =IF( COUNTIFS(Products!$A$2:$A$501, B2) <> 1, "Check product ID", IF( COUNTIFS(Products!$A$2:$A$501, B2, Products!$E$2:$E$501, "<>") <> 1, "Missing sales volume", _xlfn.XLOOKUP(B2, Products!$A$2:$A$501, Products!$E$2:$E$501, "Check product ID") ) ) -> 1200 | I2: =IF(N2 <> "Complete", "Incomplete", E2 * H2 / 1000) -> 72 | K2: Not provided | L2: Not provided | M2: Unverified | N2: =_xlfn.IFS( COUNTIFS(Products!$A$2:$A$501, B2) <> 1, "Check product ID", OR(C2 = "", D2 = "", COUNT(E2, H2) < 2), "Missing data", OR(E2 < 0, H2 < 0), "Check negative value", TRUE, "Complete" ) -> Complete | O2: Not provided | Q2: Component records | R2: =COUNTA(A2:A501) -> 8
A3: PK002 | B3: PR002 | C3: Paint tub | D3: Plastic | E3: 250 | F3: Not provided | G3: Synthetic | H3: =IF( COUNTIFS(Products!$A$2:$A$501, B3) <> 1, "Check product ID", IF( COUNTIFS(Products!$A$2:$A$501, B3, Products!$E$2:$E$501, "<>") <> 1, "Missing sales volume", _xlfn.XLOOKUP(B3, Products!$A$2:$A$501, Products!$E$2:$E$501, "Check product ID") ) ) -> 5000 | I3: =IF(N3 <> "Complete", "Incomplete", E3 * H3 / 1000) -> 1250 | K3: Not provided | L3: Not provided | M3: Unverified | N3: =_xlfn.IFS( COUNTIFS(Products!$A$2:$A$501, B3) <> 1, "Check product ID", OR(C3 = "", D3 = "", COUNT(E3, H3) < 2), "Missing data", OR(E3 < 0, H3 < 0), "Check negative value", TRUE, "Complete" ) -> Complete | O3: Not provided | Q3: Complete weight records | R3: =COUNTIFS(N2:N501, "Complete") -> 8
A4: PK003 | B4: PR002 | C4: Tub lid | D4: Plastic | E4: 50 | F4: Not provided | G4: Synthetic | H4: =IF( COUNTIFS(Products!$A$2:$A$501, B4) <> 1, "Check product ID", IF( COUNTIFS(Products!$A$2:$A$501, B4, Products!$E$2:$E$501, "<>") <> 1, "Missing sales volume", _xlfn.XLOOKUP(B4, Products!$A$2:$A$501, Products!$E$2:$E$501, "Check product ID") ) ) -> 5000 | I4: =IF(N4 <> "Complete", "Incomplete", E4 * H4 / 1000) -> 250 | K4: Not provided | L4: Not provided | M4: Unverified | N4: =_xlfn.IFS( COUNTIFS(Products!$A$2:$A$501, B4) <> 1, "Check product ID", OR(C4 = "", D4 = "", COUNT(E4, H4) < 2), "Missing data", OR(E4 < 0, H4 < 0), "Check negative value", TRUE, "Complete" ) -> Complete | O4: Not provided | Q4: Weight data completion | R4: =IF(R2 = 0, "n.a.", R3 / R2) -> 1
A5: PK004 | B5: PR003 | C5: Outer box | D5: Cardboard | E5: 120 | F5: Not provided | G5: Synthetic | H5: =IF( COUNTIFS(Products!$A$2:$A$501, B5) <> 1, "Check product ID", IF( COUNTIFS(Products!$A$2:$A$501, B5, Products!$E$2:$E$501, "<>") <> 1, "Missing sales volume", _xlfn.XLOOKUP(B5, Products!$A$2:$A$501, Products!$E$2:$E$501, "Check product ID") ) ) -> 3000 | I5: =IF(N5 <> "Complete", "Incomplete", E5 * H5 / 1000) -> 360 | K5: Not provided | L5: Not provided | M5: Unverified | N5: =_xlfn.IFS( COUNTIFS(Products!$A$2:$A$501, B5) <> 1, "Check product ID", OR(C5 = "", D5 = "", COUNT(E5, H5) < 2), "Missing data", OR(E5 < 0, H5 < 0), "Check negative value", TRUE, "Complete" ) -> Complete | O5: Not provided | Q5: Verified weight records | R5: =COUNTIFS(F2:F501, "Verified", O2:O501, "<>", O2:O501, "<>Not provided") -> 0
A6: PK005 | B6: PR004 | C6: Outer box | D6: Cardboard | E6: 180 | F6: Not provided | G6: Synthetic | H6: =IF( COUNTIFS(Products!$A$2:$A$501, B6) <> 1, "Check product ID", IF( COUNTIFS(Products!$A$2:$A$501, B6, Products!$E$2:$E$501, "<>") <> 1, "Missing sales volume", _xlfn.XLOOKUP(B6, Products!$A$2:$A$501, Products!$E$2:$E$501, "Check product ID") ) ) -> 2000 | I6: =IF(N6 <> "Complete", "Incomplete", E6 * H6 / 1000) -> 360 | K6: Not provided | L6: Not provided | M6: Unverified | N6: =_xlfn.IFS( COUNTIFS(Products!$A$2:$A$501, B6) <> 1, "Check product ID", OR(C6 = "", D6 = "", COUNT(E6, H6) < 2), "Missing data", OR(E6 < 0, H6 < 0), "Check negative value", TRUE, "Complete" ) -> Complete | O6: Not provided | Q6: Annual packaging kg | R6: =IF(R3 <> R2, "Incomplete", SUM(I2:I501)) -> 3132
A7: PK006 | B7: PR004 | C7: Protective insert | D7: Plastic | E7: 20 | F7: Not provided | G7: Synthetic | H7: =IF( COUNTIFS(Products!$A$2:$A$501, B7) <> 1, "Check product ID", IF( COUNTIFS(Products!$A$2:$A$501, B7, Products!$E$2:$E$501, "<>") <> 1, "Missing sales volume", _xlfn.XLOOKUP(B7, Products!$A$2:$A$501, Products!$E$2:$E$501, "Check product ID") ) ) -> 2000 | I7: =IF(N7 <> "Complete", "Incomplete", E7 * H7 / 1000) -> 40 | K7: Not provided | L7: Not provided | M7: Unverified | N7: =_xlfn.IFS( COUNTIFS(Products!$A$2:$A$501, B7) <> 1, "Check product ID", OR(C7 = "", D7 = "", COUNT(E7, H7) < 2), "Missing data", OR(E7 < 0, H7 < 0), "Check negative value", TRUE, "Complete" ) -> Complete | O7: Not provided | Q7: Verified recycled records | R7: =COUNTIFS(M2:M501, "Verified", J2:J501, ">=0", J2:J501, "<=1", J2:J501, "<>", K2:K501, "<>", L2:L501, "<>", K2:K501, "<>Not provided", L2:L501, "<>Not provided") -> 0
A8: PK007 | B8: PR005 | C8: Outer box | D8: Cardboard | E8: 900 | F8: Not provided | G8: Synthetic | H8: =IF( COUNTIFS(Products!$A$2:$A$501, B8) <> 1, "Check product ID", IF( COUNTIFS(Products!$A$2:$A$501, B8, Products!$E$2:$E$501, "<>") <> 1, "Missing sales volume", _xlfn.XLOOKUP(B8, Products!$A$2:$A$501, Products!$E$2:$E$501, "Check product ID") ) ) -> 800 | I8: =IF(N8 <> "Complete", "Incomplete", E8 * H8 / 1000) -> 720 | K8: Not provided | L8: Not provided | M8: Unverified | N8: =_xlfn.IFS( COUNTIFS(Products!$A$2:$A$501, B8) <> 1, "Check product ID", OR(C8 = "", D8 = "", COUNT(E8, H8) < 2), "Missing data", OR(E8 < 0, H8 < 0), "Check negative value", TRUE, "Complete" ) -> Complete | O8: Not provided
A9: PK008 | B9: PR005 | C9: Protective film | D9: Plastic | E9: 100 | F9: Not provided | G9: Synthetic | H9: =IF( COUNTIFS(Products!$A$2:$A$501, B9) <> 1, "Check product ID", IF( COUNTIFS(Products!$A$2:$A$501, B9, Products!$E$2:$E$501, "<>") <> 1, "Missing sales volume", _xlfn.XLOOKUP(B9, Products!$A$2:$A$501, Products!$E$2:$E$501, "Check product ID") ) ) -> 800 | I9: =IF(N9 <> "Complete", "Incomplete", E9 * H9 / 1000) -> 80 | K9: Not provided | L9: Not provided | M9: Unverified | N9: =_xlfn.IFS( COUNTIFS(Products!$A$2:$A$501, B9) <> 1, "Check product ID", OR(C9 = "", D9 = "", COUNT(E9, H9) < 2), "Missing data", OR(E9 < 0, H9 < 0), "Check negative value", TRUE, "Complete" ) -> Complete | O9: Not provided
Q10: Material | R10: Annual kg | S10: Chart zero baseline
Q11: Plastic | R11: =IF(R3 <> R2, "Incomplete", SUMIFS(I2:I501, D2:D501, Q11)) -> 1692 | S11: =0 -> 0
Q12: Cardboard | R12: =IF(R3 <> R2, "Incomplete", SUMIFS(I2:I501, D2:D501, Q12)) -> 1440 | S12: =0 -> 0
Q15: The 80% tools-packaging claim remains in Suppliers. No percentage is assigned to an individual component until its coverage, material source and supporting evidence are confirmed. Blank verified percentages mean unknown, not zero.

Sheet ESG_Monthly
A1: Month | B1: Site_ID | C1: Electricity_kWh | D1: Gas_kWh_GCV | E1: Total_Waste_kg | F1: Recycled_Waste_kg | G1: Data_Type | H1: Electricity_CO2_kg | I1: Gas_CO2_kg | J1: Recycling_Rate | K1: Record_Status | L1: Factor | M1: kg_CO2_per_kWh | N1: Year | O1: Status | P1: Source_URL | U1: Month | V1: Electricity CO2 kg | W1: Gas CO2 kg
A2: 45658 | B2: STORE01 | C2: 12000 | D2: 18000 | E2: 1200 | F2: 720 | G2: Synthetic | H2: =IF(OR(COUNT(C2, $M$2) < 2, MIN(C2, $M$2) < 0), "", C2 * $M$2) -> 2373.6 | I2: =IF(OR(COUNT(D2, $M$3) < 2, MIN(D2, $M$3) < 0), "", D2 * $M$3) -> 3303 | J2: =IF(OR(COUNT(E2:F2) < 2, E2 = 0, F2 > E2), "", F2 / E2) -> 0.6 | K2: =_xlfn.IFS( COUNT(C2:F2) < 4, "Missing input", MIN(C2:F2) < 0, "Check negative value", F2 > E2, "Check waste totals", TRUE, "Complete" ) -> Complete | L2: Electricity consumption | M2: 0.1978 | N2: 2025 | O2: Provisional | P2: https://www.seai.ie/data-and-insights/seai-statistics/conversion-factors | U2: =TEXT(A2, "mmm") -> Jan | V2: =H2 -> 2373.6 | W2: =I2 -> 3303
A3: 45689 | B3: STORE01 | C3: 11200 | D3: 16000 | E3: 1100 | F3: 682 | G3: Synthetic | H3: =IF(OR(COUNT(C3, $M$2) < 2, MIN(C3, $M$2) < 0), "", C3 * $M$2) -> 2215.36 | I3: =IF(OR(COUNT(D3, $M$3) < 2, MIN(D3, $M$3) < 0), "", D3 * $M$3) -> 2936 | J3: =IF(OR(COUNT(E3:F3) < 2, E3 = 0, F3 > E3), "", F3 / E3) -> 0.62 | K3: =_xlfn.IFS( COUNT(C3:F3) < 4, "Missing input", MIN(C3:F3) < 0, "Check negative value", F3 > E3, "Check waste totals", TRUE, "Complete" ) -> Complete | L3: Natural gas GCV | M3: 0.1835 | N3: 2025 | O3: Provisional | P3: https://www.seai.ie/data-and-insights/seai-statistics/conversion-factors | U3: =TEXT(A3, "mmm") -> Feb | V3: =H3 -> 2215.36 | W3: =I3 -> 2936
A4: 45717 | B4: STORE01 | C4: 10800 | D4: 13000 | E4: 1300 | F4: 819 | G4: Synthetic | H4: =IF(OR(COUNT(C4, $M$2) < 2, MIN(C4, $M$2) < 0), "", C4 * $M$2) -> 2136.24 | I4: =IF(OR(COUNT(D4, $M$3) < 2, MIN(D4, $M$3) < 0), "", D4 * $M$3) -> 2385.5 | J4: =IF(OR(COUNT(E4:F4) < 2, E4 = 0, F4 > E4), "", F4 / E4) -> 0.63 | K4: =_xlfn.IFS( COUNT(C4:F4) < 4, "Missing input", MIN(C4:F4) < 0, "Check negative value", F4 > E4, "Check waste totals", TRUE, "Complete" ) -> Complete | U4: =TEXT(A4, "mmm") -> Mar | V4: =H4 -> 2136.24 | W4: =I4 -> 2385.5
A5: 45748 | B5: STORE01 | C5: 10200 | D5: 9000 | E5: 1500 | F5: 975 | G5: Synthetic | H5: =IF(OR(COUNT(C5, $M$2) < 2, MIN(C5, $M$2) < 0), "", C5 * $M$2) -> 2017.56 | I5: =IF(OR(COUNT(D5, $M$3) < 2, MIN(D5, $M$3) < 0), "", D5 * $M$3) -> 1651.5 | J5: =IF(OR(COUNT(E5:F5) < 2, E5 = 0, F5 > E5), "", F5 / E5) -> 0.65 | K5: =_xlfn.IFS( COUNT(C5:F5) < 4, "Missing input", MIN(C5:F5) < 0, "Check negative value", F5 > E5, "Check waste totals", TRUE, "Complete" ) -> Complete | L5: Source | M5: https://www.seai.ie/data-and-insights/seai-statistics/conversion-factors | U5: =TEXT(A5, "mmm") -> Apr | V5: =H5 -> 2017.56 | W5: =I5 -> 1651.5
A6: 45778 | B6: STORE01 | C6: 10000 | D6: 5000 | E6: 1600 | F6: 1072 | G6: Synthetic | H6: =IF(OR(COUNT(C6, $M$2) < 2, MIN(C6, $M$2) < 0), "", C6 * $M$2) -> 1978 | I6: =IF(OR(COUNT(D6, $M$3) < 2, MIN(D6, $M$3) < 0), "", D6 * $M$3) -> 917.5 | J6: =IF(OR(COUNT(E6:F6) < 2, E6 = 0, F6 > E6), "", F6 / E6) -> 0.67 | K6: =_xlfn.IFS( COUNT(C6:F6) < 4, "Missing input", MIN(C6:F6) < 0, "Check negative value", F6 > E6, "Check waste totals", TRUE, "Complete" ) -> Complete | U6: =TEXT(A6, "mmm") -> May | V6: =H6 -> 1978 | W6: =I6 -> 917.5
A7: 45809 | B7: STORE01 | C7: 9800 | D7: 2500 | E7: 1700 | F7: 1173 | G7: Synthetic | H7: =IF(OR(COUNT(C7, $M$2) < 2, MIN(C7, $M$2) < 0), "", C7 * $M$2) -> 1938.44 | I7: =IF(OR(COUNT(D7, $M$3) < 2, MIN(D7, $M$3) < 0), "", D7 * $M$3) -> 458.75 | J7: =IF(OR(COUNT(E7:F7) < 2, E7 = 0, F7 > E7), "", F7 / E7) -> 0.69 | K7: =_xlfn.IFS( COUNT(C7:F7) < 4, "Missing input", MIN(C7:F7) < 0, "Check negative value", F7 > E7, "Check waste totals", TRUE, "Complete" ) -> Complete | L7: CO2 estimates only. Electricity includes network losses and excludes emissions arising outside Ireland. The factor covers more than Scope 2 alone. A complete Scope 1 and Scope 2 CO2e inventory remains pending. | U7: =TEXT(A7, "mmm") -> Jun | V7: =H7 -> 1938.44 | W7: =I7 -> 458.75
A8: 45839 | B8: STORE01 | C8: 10000 | D8: 1500 | E8: 1800 | F8: 1260 | G8: Synthetic | H8: =IF(OR(COUNT(C8, $M$2) < 2, MIN(C8, $M$2) < 0), "", C8 * $M$2) -> 1978 | I8: =IF(OR(COUNT(D8, $M$3) < 2, MIN(D8, $M$3) < 0), "", D8 * $M$3) -> 275.25 | J8: =IF(OR(COUNT(E8:F8) < 2, E8 = 0, F8 > E8), "", F8 / E8) -> 0.7 | K8: =_xlfn.IFS( COUNT(C8:F8) < 4, "Missing input", MIN(C8:F8) < 0, "Check negative value", F8 > E8, "Check waste totals", TRUE, "Complete" ) -> Complete | U8: =TEXT(A8, "mmm") -> Jul | V8: =H8 -> 1978 | W8: =I8 -> 275.25
A9: 45870 | B9: STORE01 | C9: 10100 | D9: 1500 | E9: 1750 | F9: 1260 | G9: Synthetic | H9: =IF(OR(COUNT(C9, $M$2) < 2, MIN(C9, $M$2) < 0), "", C9 * $M$2) -> 1997.78 | I9: =IF(OR(COUNT(D9, $M$3) < 2, MIN(D9, $M$3) < 0), "", D9 * $M$3) -> 275.25 | J9: =IF(OR(COUNT(E9:F9) < 2, E9 = 0, F9 > E9), "", F9 / E9) -> 0.72 | K9: =_xlfn.IFS( COUNT(C9:F9) < 4, "Missing input", MIN(C9:F9) < 0, "Check negative value", F9 > E9, "Check waste totals", TRUE, "Complete" ) -> Complete | U9: =TEXT(A9, "mmm") -> Aug | V9: =H9 -> 1997.78 | W9: =I9 -> 275.25
A10: 45901 | B10: STORE01 | C10: 10600 | D10: 4000 | E10: 1500 | F10: 1095 | G10: Synthetic | H10: =IF(OR(COUNT(C10, $M$2) < 2, MIN(C10, $M$2) < 0), "", C10 * $M$2) -> 2096.68 | I10: =IF(OR(COUNT(D10, $M$3) < 2, MIN(D10, $M$3) < 0), "", D10 * $M$3) -> 734 | J10: =IF(OR(COUNT(E10:F10) < 2, E10 = 0, F10 > E10), "", F10 / E10) -> 0.73 | K10: =_xlfn.IFS( COUNT(C10:F10) < 4, "Missing input", MIN(C10:F10) < 0, "Check negative value", F10 > E10, "Check waste totals", TRUE, "Complete" ) -> Complete | U10: =TEXT(A10, "mmm") -> Sep | V10: =H10 -> 2096.68 | W10: =I10 -> 734
A11: 45931 | B11: STORE01 | C11: 11400 | D11: 8000 | E11: 1400 | F11: 1036 | G11: Synthetic | H11: =IF(OR(COUNT(C11, $M$2) < 2, MIN(C11, $M$2) < 0), "", C11 * $M$2) -> 2254.92 | I11: =IF(OR(COUNT(D11, $M$3) < 2, MIN(D11, $M$3) < 0), "", D11 * $M$3) -> 1468 | J11: =IF(OR(COUNT(E11:F11) < 2, E11 = 0, F11 > E11), "", F11 / E11) -> 0.74 | K11: =_xlfn.IFS( COUNT(C11:F11) < 4, "Missing input", MIN(C11:F11) < 0, "Check negative value", F11 > E11, "Check waste totals", TRUE, "Complete" ) -> Complete | L11: Gas inputs use GCV. These activity inputs are synthetic and have no bills or waste transfer records attached. The waste figures describe store waste, not packaging sold with products. | U11: =TEXT(A11, "mmm") -> Oct | V11: =H11 -> 2254.92 | W11: =I11 -> 1468
A12: 45962 | B12: STORE01 | C12: 12200 | D12: 13000 | E12: 1500 | F12: 1140 | G12: Synthetic | H12: =IF(OR(COUNT(C12, $M$2) < 2, MIN(C12, $M$2) < 0), "", C12 * $M$2) -> 2413.16 | I12: =IF(OR(COUNT(D12, $M$3) < 2, MIN(D12, $M$3) < 0), "", D12 * $M$3) -> 2385.5 | J12: =IF(OR(COUNT(E12:F12) < 2, E12 = 0, F12 > E12), "", F12 / E12) -> 0.76 | K12: =_xlfn.IFS( COUNT(C12:F12) < 4, "Missing input", MIN(C12:F12) < 0, "Check negative value", F12 > E12, "Check waste totals", TRUE, "Complete" ) -> Complete | U12: =TEXT(A12, "mmm") -> Nov | V12: =H12 -> 2413.16 | W12: =I12 -> 2385.5
A13: 45992 | B13: STORE01 | C13: 13000 | D13: 17000 | E13: 1800 | F13: 1404 | G13: Synthetic | H13: =IF(OR(COUNT(C13, $M$2) < 2, MIN(C13, $M$2) < 0), "", C13 * $M$2) -> 2571.4 | I13: =IF(OR(COUNT(D13, $M$3) < 2, MIN(D13, $M$3) < 0), "", D13 * $M$3) -> 3119.5 | J13: =IF(OR(COUNT(E13:F13) < 2, E13 = 0, F13 > E13), "", F13 / E13) -> 0.78 | K13: =_xlfn.IFS( COUNT(C13:F13) < 4, "Missing input", MIN(C13:F13) < 0, "Check negative value", F13 > E13, "Check waste totals", TRUE, "Complete" ) -> Complete | U13: =TEXT(A13, "mmm") -> Dec | V13: =H13 -> 2571.4 | W13: =I13 -> 3119.5
A14: Annual Total | C14: =IF(OR(COUNT(C2:C13) <> 12, MIN(C2:C13) < 0), "Incomplete", SUM(C2:C13)) -> 131300 | D14: =IF(OR(COUNT(D2:D13) <> 12, MIN(D2:D13) < 0), "Incomplete", SUM(D2:D13)) -> 108500 | E14: =IF(OR(COUNT(E2:E13) <> 12, MIN(E2:E13) < 0), "Incomplete", SUM(E2:E13)) -> 18150 | F14: =IF(OR(COUNT(F2:F13) <> 12, MIN(F2:F13) < 0), "Incomplete", SUM(F2:F13)) -> 12636 | H14: =IF(OR(COUNT(H2:H13) <> 12, MIN(H2:H13) < 0), "Incomplete", SUM(H2:H13)) -> 25971.14 | I14: =IF(OR(COUNT(I2:I13) <> 12, MIN(I2:I13) < 0), "Incomplete", SUM(I2:I13)) -> 19909.75 | J14: =IF(COUNTIFS(K2:K13, "Complete") <> 12, "Check records", IF(E14 = 0, "n.a.", F14 / E14)) -> 0.69619835
L15: Factors checked on | M15: 46292

Sheet Regulations
A1: Regulation_ID | B1: Topic | C1: Framework | D1: Applicability_to_Demo | E1: Milestone_Type | F1: Application_Date | G1: Internal_Owner | H1: Required_Action | I1: Readiness_Status | J1: Action_ID | K1: Source | L1: Source_URL | M1: Checked_On | N1: Next_Source_Review | O1: Date_Status | P1: Days_to_Application | Q1: Scope_Notes | S1: Register scope | T1: Value
A2: REG001 | B2: Environmental claims | C2: S.I. 124/2026 and Directive (EU) 2024/825 | D2: Relevant to consumer-facing sustainability claims. | E2: Application date | F2: 46292 | G2: Commercial and Marketing | H2: Review claim wording and hold unsupported claims. | I2: Not assessed | J2: ACT007 | K2: CCPC | L2: https://www.ccpc.ie/information-for-businesses/guidance-for-businesses/consumer-protection-guidance/european-union-(empowering-consumers-for-the-green-transition)-regulations-2026 | M2: 46292 | N2: 46322 | O2: =IF(F2 = "", "Ongoing", IF(Dashboard!$C$4 >= F2, "Application date reached", "Upcoming")) -> Application date reached | P2: =IF(F2 = "", "", MAX(0, F2 - Dashboard!$C$4)) -> 0 | Q2: Evidence alone does not make a broad claim acceptable. Obtain a wording review. | S2: Topics covered | T2: =COUNTA(A2:A7) -> 6
A3: REG002 | B3: Packaging requirements | C3: Regulation (EU) 2025/40 | D3: Packaged goods are relevant. Confirm the retailer role and individual duties. | E3: General application | F3: 46246 | G3: Sustainability Manager | H3: Map relevant requirements and build component-level evidence. | I3: Not assessed | J3: ACT013 | K3: European Commission | L3: https://environment.ec.europa.eu/news/new-eu-rules-packaging-enter-application-2026-08-11_en | M3: 46292 | N3: 46322 | O3: =IF(F3 = "", "Ongoing", IF(Dashboard!$C$4 >= F3, "Application date reached", "Upcoming")) -> Application date reached | P3: =IF(F3 = "", "", MAX(0, F3 - Dashboard!$C$4)) -> 0 | Q3: Implementation is phased. The general application date is not the start date of every labelling or recycled-content requirement. | S3: Not assessed | T3: =COUNTIFS(I2:I7, "Not assessed") -> 6
A4: REG003 | B4: Deforestation and timber | C4: Regulation (EU) 2023/1115 as amended | D4: Screen timber panel and wooden chair by commodity code, role and business size. | E4: Conditional application | F4: 46386 | G4: Commercial and Sustainability | H4: Confirm scope, traceability needs and the applicable start date. | I4: Not assessed | J4: ACT008 | K4: European Commission | L4: https://environment.ec.europa.eu/topics/forests/deforestation/regulation-deforestation-free-products_en | M4: 46292 | N4: 46322 | O4: =IF(F4 = "", "Ongoing", IF(Dashboard!$C$4 >= F4, "Application date reached", "Upcoming")) -> Upcoming | P4: =IF(F4 = "", "", MAX(0, F4 - Dashboard!$C$4)) -> 94 | Q4: 30-Dec-2026 applies to large/medium operators and small/micro operators already under EUTR. Other small/micro operators: 30-Jun-2027. A sourcing certificate alone is insufficient. | S4: Source checks due | T4: =COUNTIFS(N2:N7, "<" & Dashboard!$C$4) -> 0
A5: REG004 | B5: Paint VOC content | C5: S.I. 564/2012 as amended | D5: Screen the paint product category and its specific VOC limit. | E5: Ongoing obligation | G5: Paint Category Manager | H5: Check technical sheet, product category and VOC labelling. | I5: Not assessed | J5: ACT002 | K5: EPA | L5: https://www.epa.ie/our-services/compliance--enforcement/air/decorative-paints/decorative-paints-regulations/ | M5: 46292 | N5: 46322 | O5: =IF(F5 = "", "Ongoing", IF(Dashboard!$C$4 >= F5, "Application date reached", "Upcoming")) -> Ongoing | P5: =IF(F5 = "", "", MAX(0, F5 - Dashboard!$C$4)) | Q5: Low VOC is a claim. The legal limit depends on the paint category; do not use one universal threshold.
A6: REG005 | B6: Lighting information | C6: Regulation (EU) 2019/2015 | D6: Confirm whether the product is a light source or a containing product. | E6: Ongoing obligation | G6: Lighting Category Manager | H6: Check model classification, applicable label and product information. | I6: Not assessed | J6: ACT012 | K6: SEAI | L6: https://www.seai.ie/plan-your-energy-journey/for-your-business/energy-efficient-products/energy-tyre-labelling-and-ecodesign/lighting-products | M6: 46292 | N6: 46322 | O6: =IF(F6 = "", "Ongoing", IF(Dashboard!$C$4 >= F6, "Application date reached", "Upcoming")) -> Ongoing | P6: =IF(F6 = "", "", MAX(0, F6 - Dashboard!$C$4)) | Q6: Check EPREL and supplier model references where applicable. Energy labelling and ecodesign duties differ by role. | S6: Focused screening register for the sample products. Internal task due dates are in Actions. No legal-compliance conclusion is made from a completed task.
A7: REG006 | B7: Electrical waste take-back | C7: Irish WEEE obligations | D7: Relevant to the lighting product. Check importer as well as retailer duties. | E7: Ongoing obligation | G7: Operations Manager | H7: Check producer registration, take-back notices and collection records. | I7: Not assessed | J7: ACT011 | K7: EPA | L7: https://www.epa.ie/our-services/compliance--enforcement/waste/weee/information-for-distributors-of-eee-and-batteries/ | M7: 46292 | N7: 46322 | O7: =IF(F7 = "", "Ongoing", IF(Dashboard!$C$4 >= F7, "Application date reached", "Upcoming")) -> Ongoing | P7: =IF(F7 = "", "", MAX(0, F7 - Dashboard!$C$4)) | Q7: Retailer duties include take-back and record keeping. Confirm the precise product and sales-channel requirements.

Sheet Costs
A1: Cost_ID | B1: Action_ID | C1: Cost_Item | D1: Cost_Type | E1: Quantity | F1: Unit | G1: Rate_EUR | H1: Base_Cost_EUR | I1: Contingency_Rate | J1: Contingency_EUR | K1: Planned_Cost_EUR | L1: Actual_Cost_EUR | M1: Variance_EUR | N1: Estimate_Basis | O1: Internal_Owner | Q1: Cost assumptions | R1: Value
A2: C001 | B2: ACT001 | C2: Supplier evidence review | D2: Staff time | E2: 10 | F2: hours | G2: 35 | H2: =IF(COUNT(E2, G2) < 2, "Incomplete", E2 * G2) -> 350 | I2: =$R$2 -> 0.1 | J2: =IF(COUNT(H2, I2) < 2, "Incomplete", H2 * I2) -> 35 | K2: =IF(COUNT(H2, J2) < 2, "Incomplete", H2 + J2) -> 385 | M2: =IF(COUNT(L2, K2) < 2, "", L2 - K2) | N2: Synthetic planning allowance; no supplier quote. | O2: =_xlfn.XLOOKUP(B2, Actions!$A$2:$A$14, Actions!$E$2:$E$14, "Check action ID") -> Garden Category Manager | Q2: Contingency allowance | R2: 0.1
A3: C002 | B3: ACT006 | C3: Packaging measurement | D3: Staff time | E3: 8 | F3: hours | G3: 30 | H3: =IF(COUNT(E3, G3) < 2, "Incomplete", E3 * G3) -> 240 | I3: =$R$2 -> 0.1 | J3: =IF(COUNT(H3, I3) < 2, "Incomplete", H3 * I3) -> 24 | K3: =IF(COUNT(H3, J3) < 2, "Incomplete", H3 + J3) -> 264 | M3: =IF(COUNT(L3, K3) < 2, "", L3 - K3) | N3: Synthetic planning allowance; no supplier quote. | O3: =_xlfn.XLOOKUP(B3, Actions!$A$2:$A$14, Actions!$E$2:$E$14, "Check action ID") -> Commercial and Suppliers | Q3: Resource cost incl. contingency | R3: =K12 -> 3806
A4: C003 | B4: ACT007 | C4: Environmental claim review | D4: Staff time | E4: 8 | F4: hours | G4: 60 | H4: =IF(COUNT(E4, G4) < 2, "Incomplete", E4 * G4) -> 480 | I4: =$R$2 -> 0.1 | J4: =IF(COUNT(H4, I4) < 2, "Incomplete", H4 * I4) -> 48 | K4: =IF(COUNT(H4, J4) < 2, "Incomplete", H4 + J4) -> 528 | M4: =IF(COUNT(L4, K4) < 2, "", L4 - K4) | N4: Synthetic planning allowance; no supplier quote. | O4: =_xlfn.XLOOKUP(B4, Actions!$A$2:$A$14, Actions!$E$2:$E$14, "Check action ID") -> Commercial and Marketing | Q4: Staff time incl. contingency | R4: =SUMIFS(K2:K11, D2:D11, "Staff time") -> 3674
A5: C004 | B5: ACT008 | C5: Timber scope and traceability review | D5: Staff time | E5: 12 | F5: hours | G5: 45 | H5: =IF(COUNT(E5, G5) < 2, "Incomplete", E5 * G5) -> 540 | I5: =$R$2 -> 0.1 | J5: =IF(COUNT(H5, I5) < 2, "Incomplete", H5 * I5) -> 54 | K5: =IF(COUNT(H5, J5) < 2, "Incomplete", H5 + J5) -> 594 | M5: =IF(COUNT(L5, K5) < 2, "", L5 - K5) | N5: Synthetic planning allowance; no supplier quote. | O5: =_xlfn.XLOOKUP(B5, Actions!$A$2:$A$14, Actions!$E$2:$E$14, "Check action ID") -> Sustainability Manager | Q5: Equipment incl. contingency | R5: =SUMIFS(K2:K11, D2:D11, "Equipment") -> 132
A6: C005 | B6: ACT009 | C6: Activity data reconciliation | D6: Staff time | E6: 6 | F6: hours | G6: 35 | H6: =IF(COUNT(E6, G6) < 2, "Incomplete", E6 * G6) -> 210 | I6: =$R$2 -> 0.1 | J6: =IF(COUNT(H6, I6) < 2, "Incomplete", H6 * I6) -> 21 | K6: =IF(COUNT(H6, J6) < 2, "Incomplete", H6 + J6) -> 231 | M6: =IF(COUNT(L6, K6) < 2, "", L6 - K6) | N6: Synthetic planning allowance; no supplier quote. | O6: =_xlfn.XLOOKUP(B6, Actions!$A$2:$A$14, Actions!$E$2:$E$14, "Check action ID") -> Operations and Finance | Q6: Actual amounts entered | R6: =COUNT(L2:L11) -> 0
A7: C006 | B7: ACT010 | C7: GHG inventory boundary review | D7: Staff time | E7: 8 | F7: hours | G7: 60 | H7: =IF(COUNT(E7, G7) < 2, "Incomplete", E7 * G7) -> 480 | I7: =$R$2 -> 0.1 | J7: =IF(COUNT(H7, I7) < 2, "Incomplete", H7 * I7) -> 48 | K7: =IF(COUNT(H7, J7) < 2, "Incomplete", H7 + J7) -> 528 | M7: =IF(COUNT(L7, K7) < 2, "", L7 - K7) | N7: Synthetic planning allowance; no supplier quote. | O7: =_xlfn.XLOOKUP(B7, Actions!$A$2:$A$14, Actions!$E$2:$E$14, "Check action ID") -> Sustainability Manager
A8: C007 | B8: ACT011 | C8: WEEE procedure review | D8: Staff time | E8: 4 | F8: hours | G8: 35 | H8: =IF(COUNT(E8, G8) < 2, "Incomplete", E8 * G8) -> 140 | I8: =$R$2 -> 0.1 | J8: =IF(COUNT(H8, I8) < 2, "Incomplete", H8 * I8) -> 14 | K8: =IF(COUNT(H8, J8) < 2, "Incomplete", H8 + J8) -> 154 | M8: =IF(COUNT(L8, K8) < 2, "", L8 - K8) | N8: Synthetic planning allowance; no supplier quote. | O8: =_xlfn.XLOOKUP(B8, Actions!$A$2:$A$14, Actions!$E$2:$E$14, "Check action ID") -> Operations Manager
A9: C008 | B9: ACT012 | C9: Lighting model review | D9: Staff time | E9: 4 | F9: hours | G9: 45 | H9: =IF(COUNT(E9, G9) < 2, "Incomplete", E9 * G9) -> 180 | I9: =$R$2 -> 0.1 | J9: =IF(COUNT(H9, I9) < 2, "Incomplete", H9 * I9) -> 18 | K9: =IF(COUNT(H9, J9) < 2, "Incomplete", H9 + J9) -> 198 | M9: =IF(COUNT(L9, K9) < 2, "", L9 - K9) | N9: Synthetic planning allowance; no supplier quote. | O9: =_xlfn.XLOOKUP(B9, Actions!$A$2:$A$14, Actions!$E$2:$E$14, "Check action ID") -> Lighting Category Manager | Q9: Staff time is an opportunity-cost allowance, not automatically additional cash spend. Equipment is a planning estimate. VAT, scheme fees, fines and mandatory tariffs are not modelled. Blank actuals mean unknown. No expenditure has been approved.
A10: C009 | B10: ACT013 | C10: Packaging obligations review | D10: Staff time | E10: 12 | F10: hours | G10: 60 | H10: =IF(COUNT(E10, G10) < 2, "Incomplete", E10 * G10) -> 720 | I10: =$R$2 -> 0.1 | J10: =IF(COUNT(H10, I10) < 2, "Incomplete", H10 * I10) -> 72 | K10: =IF(COUNT(H10, J10) < 2, "Incomplete", H10 + J10) -> 792 | M10: =IF(COUNT(L10, K10) < 2, "", L10 - K10) | N10: Synthetic planning allowance; no supplier quote. | O10: =_xlfn.XLOOKUP(B10, Actions!$A$2:$A$14, Actions!$E$2:$E$14, "Check action ID") -> Sustainability Manager
A11: C010 | B11: ACT006 | C11: Packaging weighing scale | D11: Equipment | E11: 1 | F11: item | G11: 120 | H11: =IF(COUNT(E11, G11) < 2, "Incomplete", E11 * G11) -> 120 | I11: =$R$2 -> 0.1 | J11: =IF(COUNT(H11, I11) < 2, "Incomplete", H11 * I11) -> 12 | K11: =IF(COUNT(H11, J11) < 2, "Incomplete", H11 + J11) -> 132 | M11: =IF(COUNT(L11, K11) < 2, "", L11 - K11) | N11: Synthetic planning allowance; no supplier quote. | O11: =_xlfn.XLOOKUP(B11, Actions!$A$2:$A$14, Actions!$E$2:$E$14, "Check action ID") -> Commercial and Suppliers
C12: Total resource cost | H12: =IF(COUNT(H2:H11) < 10, "Incomplete", SUM(H2:H11)) -> 3460 | J12: =IF(COUNT(J2:J11) < 10, "Incomplete", SUM(J2:J11)) -> 346 | K12: =IF(COUNT(K2:K11) < 10, "Incomplete", SUM(K2:K11)) -> 3806 | L12: =IF(COUNT(L2:L11) < 10, "Not complete", SUM(L2:L11)) -> Not complete | M12: =IF(COUNT(L2:L11) < 10, "", L12 - K12)

Sheet README
A2: About this project
A4: Purpose | B4: Build a sustainability readiness system for a fictional Irish DIY retailer. Track supplier evidence, products, packaging, environmental KPIs, regulatory topics, costs and corrective actions.
A6: Owner | B6: Sagar Malik. Portfolio demonstration inspired by the green colour direction of Woodie's. It is not a Woodie's operational workbook or an official brand template.
A8: Data boundary | B8: Five suppliers, five products, eight packaging components and one store with twelve months of 2025 activity. Existing activity and supplier inputs have been retained.
A10: Review date | B10: Dashboard C4 is an editable snapshot date. It starts at 27-Sep-2026. Changing it updates due statuses. Legal sources were checked on 27-Sep-2026.
A12: Current evidence | B12: All five supplier claims remain Unverified. Descriptions such as technical sheet received are synthetic scenario text; no actual supplier documents were provided.
A14: Evidence readiness | B14: Suppliers V4 counts records ready for approval divided by all supplier records. A claim needs verification, a real reference and current evidence before it is ready for a wording review.
A16: Weight data completion | B16: Packaging R4 counts component rows with usable keys, material, component, weight and volume. Completeness does not mean that weights are verified.
A18: Recycled material | B18: Verified recycled percentages stay blank until evidence confirms the percentage, packaging components and material source. Zero would mean a known absence of recycled content.
A20: Monthly calculations | B20: Energy use multiplied by the relevant kg CO2/kWh factor gives kg CO2. Annual recycling is recycled waste divided by total waste over the same year.
A22: Emissions boundary | B22: Current outputs are energy-related CO2 estimates. A full greenhouse-gas inventory needs a boundary, further sources and gases, and an appropriate electricity accounting method.
A24: Legal register | B24: Six screening topics are included for the sample products. Source dates, conditional application dates and internal tasks are kept separate. Scope and readiness require review.
A26: Costs | B26: Quantity multiplied by rate gives base cost. A shared 10% planning contingency is added. Staff time is included as a resource cost. Actual amounts are unknown.
... A38: Further explanation | B38: See ESG_Project_Walkthrough.docx for the build steps, formulas, sources, dashboard choices, testing and interview preparation.
